{
    "InputElements": {
        "Username": {
            "elementType": "input",
            "elementConfig": {
                "type": "text",
                "placeholder": "Your Name"
            },
            "value": "",
            "validation": {
                "required": true
            },
            "valid": false,
            "touched": false
        },
        "Address": {
            "elementType": "textarea",
            "elementConfig": {
                "type": "textarea",
                "placeholder": "Address"
            },
            "value": "",
            "validation": {
                "required": true
            },
            "valid": false,
            "touched": false
        },
        "ZipCode": {
            "elementType": "input",
            "elementConfig": {
                "type": "number",
                "placeholder": "ZIP Code"
            },
            "value": "",
            "validation": {
                "required": true,
                "minLength": 6,
                "maxLength": 6
            },
            "valid": false,
            "touched": false
        },
        "Country": {
            "elementType": "input",
            "elementConfig": {
                "type": "text",
                "placeholder": "Country"
            },
            "value": "",
            "validation": {
                "required": true
            },
            "valid": false,
            "touched": false
        },
        "Email": {
            "elementType": "input",
            "elementConfig": {
                "type": "email",
                "placeholder": "Your E-Mail"
            },
            "value": "",
            "validation": {
                "required": true
            },
            "valid": false,
            "touched": false
        },
        "Password": {
            "elementType": "input",
            "elementConfig": {
                "type": "password",
                "placeholder": "Your password"
            },
            "value": "",
            "validation": {
                "required": true
            },
            "valid": false,
            "touched": false
        },
        "DeliveryMethod": {
            "elementType": "select",
            "elementConfig": {
                "options": [
                    {
                        "value": "fastest",
                        "displayValue": "Fastest"
                    },
                    {
                        "value": "cheapest",
                        "displayValue": "Cheapest"
                    }
                ]
            },
            "value": "",
            "validation": {
                "required": true
            },
            "valid": false
        }
    },
    "Button": {
        "elementType": "button",
        "elementConfig": {
            "type": "submit",
            "variant": "contained",
            "color": "primary"
        },
        "text": "Submit",
        "className": "text-right"
    },
    "formIsValid": true,
    "loading": false
}